{
  "time": "April 03, 2026  02:10:52 PM",
  "summary": "Market sentiment: Fear & Greed 9/100 \u2014 Extreme Fear. Also watching: SOL, LINK. No trades taken this scan. Bot is being patient \u2014 all 3 signals must agree before any entry.",
  "signals": {
    "BTC-USD": {
      "price": 66750.01,
      "rsi": 48.89773023741185,
      "ema200": 67518.7722672069,
      "adx": 18.700608217137106,
      "atr": 337.2578571428593,
      "vol24": 348296437.6306227,
      "above_ema": false,
      "trending": false,
      "oversold": false,
      "vol_ok": true,
      "sl": 66075.494286,
      "tp": 68099.041429,
      "be_trigger": 67424.525714
    },
    "ETH-USD": {
      "price": 2048.68,
      "rsi": 44.878283923837046,
      "ema200": 2058.4018498749238,
      "adx": 27.140600315956075,
      "atr": 13.212142857142826,
      "vol24": 224274178.64510608,
      "above_ema": false,
      "trending": true,
      "oversold": false,
      "vol_ok": true,
      "sl": 2022.255714,
      "tp": 2101.528571,
      "be_trigger": 2075.104286
    },
    "SOL-USD": {
      "price": 79.8,
      "rsi": 58.75370919881309,
      "ema200": 83.07256557323477,
      "adx": 35.8778625954197,
      "atr": 0.6450000000000011,
      "vol24": 89748287.5709011,
      "above_ema": false,
      "trending": true,
      "oversold": false,
      "vol_ok": true,
      "sl": 78.51,
      "tp": 82.38,
      "be_trigger": 81.09
    },
    "LINK-USD": {
      "price": 8.692,
      "rsi": 65.43778801843331,
      "ema200": 8.741920348462465,
      "adx": 51.80722891566247,
      "atr": 0.0603571428571429,
      "vol24": 7359684.03906,
      "above_ema": false,
      "trending": true,
      "oversold": false,
      "vol_ok": true,
      "sl": 8.571286,
      "tp": 8.933429,
      "be_trigger": 8.812714
    },
    "XRP-USD": {
      "price": 1.3173,
      "rsi": 51.910112359550354,
      "ema200": 1.3396623640424146,
      "adx": 13.523809523809144,
      "atr": 0.008900000000000019,
      "vol24": 73950167.43742293,
      "above_ema": false,
      "trending": false,
      "oversold": false,
      "vol_ok": true,
      "sl": 1.2995,
      "tp": 1.3529,
      "be_trigger": 1.3351
    },
    "AVAX-USD": {
      "price": 8.98,
      "rsi": 85.71428571428598,
      "ema200": 8.945757478837226,
      "adx": 94.28571428571445,
      "atr": 0.0664285714285714,
      "vol24": 2748696.0345812575,
      "above_ema": true,
      "trending": true,
      "oversold": false,
      "vol_ok": false,
      "sl": 8.847143,
      "tp": 9.245714,
      "be_trigger": 9.112857
    },
    "ADA-USD": {
      "price": 0.2464,
      "rsi": 88.76404494382048,
      "ema200": 0.2476440151156861,
      "adx": 89.79591836734696,
      "atr": 0.0020214285714285707,
      "vol24": 8656345.68723253,
      "above_ema": false,
      "trending": true,
      "oversold": false,
      "vol_ok": true,
      "sl": 0.242357,
      "tp": 0.254486,
      "be_trigger": 0.250443
    }
  }
}