{
  "time": "April 03, 2026  03:04:05 PM",
  "summary": "Market sentiment: Fear & Greed 9/100 \u2014 Extreme Fear. ADA is the closest with 2 of 3 signals met. Still waiting on: RSI 92 not oversold yet (need < 35). Also watching: BTC, ETH. No trades taken this scan. Bot is being patient \u2014 all 3 signals must agree before any entry.",
  "signals": {
    "BTC-USD": {
      "price": 66952.0,
      "rsi": 60.27970787755163,
      "ema200": 67501.29998439108,
      "adx": 40.38056950027994,
      "atr": 325.8378571428589,
      "vol24": 334616710.0385802,
      "above_ema": false,
      "trending": true,
      "oversold": false,
      "vol_ok": true,
      "sl": 66300.324286,
      "tp": 68255.351429,
      "be_trigger": 67603.675714
    },
    "ETH-USD": {
      "price": 2055.31,
      "rsi": 55.42142230026346,
      "ema200": 2057.874252188235,
      "adx": 40.845070422535684,
      "atr": 12.418571428571422,
      "vol24": 196661664.07067016,
      "above_ema": false,
      "trending": true,
      "oversold": false,
      "vol_ok": true,
      "sl": 2030.472857,
      "tp": 2104.984286,
      "be_trigger": 2080.147143
    },
    "SOL-USD": {
      "price": 80.33,
      "rsi": 65.02590673575119,
      "ema200": 83.03239079062722,
      "adx": 36.603773584905205,
      "atr": 0.6321428571428578,
      "vol24": 83550569.13874817,
      "above_ema": false,
      "trending": true,
      "oversold": false,
      "vol_ok": true,
      "sl": 79.065714,
      "tp": 82.858571,
      "be_trigger": 81.594286
    },
    "LINK-USD": {
      "price": 8.729,
      "rsi": 72.83950617283958,
      "ema200": 8.740007233091953,
      "adx": 52.66272189349097,
      "atr": 0.05900000000000004,
      "vol24": 7222417.62893,
      "above_ema": false,
      "trending": true,
      "oversold": false,
      "vol_ok": true,
      "sl": 8.611,
      "tp": 8.965,
      "be_trigger": 8.847
    },
    "XRP-USD": {
      "price": 1.3214,
      "rsi": 58.351409978307906,
      "ema200": 1.339305637040043,
      "adx": 19.066147859921596,
      "atr": 0.008671428571428583,
      "vol24": 71155618.44098283,
      "above_ema": false,
      "trending": false,
      "oversold": false,
      "vol_ok": true,
      "sl": 1.304057,
      "tp": 1.356086,
      "be_trigger": 1.338743
    },
    "AVAX-USD": {
      "price": 9.02,
      "rsi": 93.5483870967743,
      "ema200": 8.944900808851658,
      "adx": 94.87179487179499,
      "atr": 0.0671428571428571,
      "vol24": 2931353.0568964626,
      "above_ema": true,
      "trending": true,
      "oversold": false,
      "vol_ok": false,
      "sl": 8.885714,
      "tp": 9.288571,
      "be_trigger": 9.154286
    },
    "ADA-USD": {
      "price": 0.2496,
      "rsi": 91.52542372881373,
      "ema200": 0.24761297794915596,
      "adx": 91.869918699187,
      "atr": 0.0021571428571428596,
      "vol24": 8683224.633282706,
      "above_ema": true,
      "trending": true,
      "oversold": false,
      "vol_ok": true,
      "sl": 0.245286,
      "tp": 0.258229,
      "be_trigger": 0.253914
    }
  }
}